<?xml version="1.0" encoding="utf-8"?><ArrayOfLocalGoverment xmlns:xsd="http://www.w3.org/2001/XMLSchema" xmlns:xsi="http://www.w3.org/2001/XMLSchema-instance"><LocalGoverment PrefCode="32" LocalGovCode="32201"><LocalGovName>松江市</LocalGovName></LocalGoverment><LocalGoverment PrefCode="32" LocalGovCode="32202"><LocalGovName>浜田市</LocalGovName></LocalGoverment><LocalGoverment PrefCode="32" LocalGovCode="32203"><LocalGovName>出雲市</LocalGovName></LocalGoverment><LocalGoverment PrefCode="32" LocalGovCode="32204"><LocalGovName>益田市</LocalGovName></LocalGoverment><LocalGoverment PrefCode="32" LocalGovCode="32205"><LocalGovName>大田市</LocalGovName></LocalGoverment><LocalGoverment PrefCode="32" LocalGovCode="32206"><LocalGovName>安来市</LocalGovName></LocalGoverment><LocalGoverment PrefCode="32" LocalGovCode="32207"><LocalGovName>江津市</LocalGovName></LocalGoverment><LocalGoverment PrefCode="32" LocalGovCode="32209"><LocalGovName>雲南市</LocalGovName></LocalGoverment><LocalGoverment PrefCode="32" LocalGovCode="32343"><LocalGovName>奥出雲町</LocalGovName></LocalGoverment><LocalGoverment PrefCode="32" LocalGovCode="32386"><LocalGovName>飯南町</LocalGovName></LocalGoverment><LocalGoverment PrefCode="32" LocalGovCode="32441"><LocalGovName>川本町</LocalGovName></LocalGoverment><LocalGoverment PrefCode="32" LocalGovCode="32448"><LocalGovName>美郷町</LocalGovName></LocalGoverment><LocalGoverment PrefCode="32" LocalGovCode="32449"><LocalGovName>邑南町</LocalGovName></LocalGoverment><LocalGoverment PrefCode="32" LocalGovCode="32501"><LocalGovName>津和野町</LocalGovName></LocalGoverment><LocalGoverment PrefCode="32" LocalGovCode="32505"><LocalGovName>吉賀町</LocalGovName></LocalGoverment><LocalGoverment PrefCode="32" LocalGovCode="32525"><LocalGovName>海士町</LocalGovName></LocalGoverment><LocalGoverment PrefCode="32" LocalGovCode="32526"><LocalGovName>西ノ島町</LocalGovName></LocalGoverment><LocalGoverment PrefCode="32" LocalGovCode="32527"><LocalGovName>知夫村</LocalGovName></LocalGoverment><LocalGoverment PrefCode="32" LocalGovCode="32528"><LocalGovName>隠岐の島町</LocalGovName></LocalGoverment></ArrayOfLocalGoverment>